excel_split_merge_tool/__init__.py
excel_split_merge_tool/main.py
excel_split_merge_tool/resources/__init__.py
excel_split_merge_tool/resources/configs.py
excel_split_merge_tool-1.0.4.dist-info/METADATA
excel_split_merge_tool-1.0.4.dist-info/WHEEL
excel_split_merge_tool-1.0.4.dist-info/top_level.txt
excel_split_merge_tool-1.0.4.dist-info/RECORD
